xterm256_converter/__init__.py
xterm256_converter/core.py
xterm256_converter/message.py
xterm256_converter/xterm256.csv
xterm256_converter-0.2.0.dist-info/LICENSE
xterm256_converter-0.2.0.dist-info/METADATA
xterm256_converter-0.2.0.dist-info/WHEEL
xterm256_converter-0.2.0.dist-info/entry_points.txt
xterm256_converter-0.2.0.dist-info/top_level.txt
xterm256_converter-0.2.0.dist-info/RECORD
