Metadata-Version: 2.1
Name: xterm256-converter
Version: 0.2.0
Summary: This util can convert hex color code to nearest xterm 256 color.
Home-page: UNKNOWN
Author: averak
Author-email: UNKNOWN
License: MIT
Platform: UNKNOWN
Classifier: Programming Language :: Python
Classifier: Programming Language :: Python :: 3.8
